README.md
setup.py
listenwicht/ActionDaemon.py
listenwicht/ActionDisplay.py
listenwicht/ActionSystemd.py
listenwicht/BurstLimiter.py
listenwicht/Configfile.py
listenwicht/Enums.py
listenwicht/FriendlyArgumentParser.py
listenwicht/LWBaseAction.py
listenwicht/Mailprocessor.py
listenwicht/MultiCommand.py
listenwicht/PrefixMatcher.py
listenwicht/ReceivedMail.py
listenwicht/__init__.py
listenwicht/__main__.py
listenwicht.egg-info/PKG-INFO
listenwicht.egg-info/SOURCES.txt
listenwicht.egg-info/dependency_links.txt
listenwicht.egg-info/entry_points.txt
listenwicht.egg-info/requires.txt
listenwicht.egg-info/top_level.txt